Pyquet/__init__.py
Pyquet/cli.py
Pyquet/mzml_converter.py
pyquetms-0.1.0.dist-info/METADATA
pyquetms-0.1.0.dist-info/WHEEL
pyquetms-0.1.0.dist-info/entry_points.txt
pyquetms-0.1.0.dist-info/top_level.txt
pyquetms-0.1.0.dist-info/RECORD
